Workbook

Sheet Raw_GA4_Traffic
A1: date | B1: session_source_medium | C1: default_channel_group | D1: campaign_name | E1: sessions | F1: total_users | G1: new_users | H1: engaged_sessions | I1: average_engagement_time_seconds | J1: event_count | K1: key_events | L1: cost_usd
A2: 2026-01-01 | B2: google / organic | C2: Organic Search | D2: organic_non_brand | E2: 131 | F2: 94 | G2: 54 | H2: 90 | I2: 121 | J2: 465 | K2: 6 | L2: 23.41
A3: 2026-01-01 | B3: google / cpc | C3: Paid Search | D3: google_ecommerce_leads | E3: 52 | F3: 39 | G3: 25 | H3: 31 | I3: 52 | J3: 186 | K3: 2 | L3: 59.34
A4: 2026-01-01 | B4: facebook / paid_social | C4: Paid Social | D4: fb_business_website_awareness | E4: 87 | F4: 73 | G4: 38 | H4: 43 | I4: 41 | J4: 259 | K4: 4 | L4: 35.59
A5: 2026-01-01 | B5: newsletter / email | C5: Email | D5: client_referral_nurture | E5: 18 | F5: 13 | G5: 7 | H5: 15 | I5: 95 | J5: 57 | K5: 1 | L5: 1.5
A6: 2026-01-01 | B6: (direct) / (none) | C6: Direct | D6: direct_none | E6: 41 | F6: 31 | G6: 20 | H6: 24 | I6: 62 | J6: 111 | K6: 2 | L6: 0
A7: 2026-01-01 | B7: partner_sites / referral | C7: Referral | D7: directory_referrals | E7: 29 | F7: 24 | G7: 14 | H7: 19 | I7: 47 | J7: 77 | K7: 1 | L7: 1.42
A8: 2026-01-02 | B8: google / organic | C8: Organic Search | D8: organic_non_brand | E8: 137 | F8: 110 | G8: 68 | H8: 89 | I8: 96 | J8: 534 | K8: 6 | L8: 27.1
A9: 2026-01-02 | B9: google / cpc | C9: Paid Search | D9: google_website_service_leads | E9: 71 | F9: 57 | G9: 31 | H9: 45 | I9: 90 | J9: 278 | K9: 4 | L9: 89.63
A10: 2026-01-02 | B10: facebook / paid_social | C10: Paid Social | D10: fb_business_website_awareness | E10: 90 | F10: 74 | G10: 44 | H10: 35 | I10: 35 | J10: 364 | K10: 1 | L10: 40.25
A11: 2026-01-02 | B11: newsletter / email | C11: Email | D11: monthly_newsletter | E11: 22 | F11: 19 | G11: 13 | H11: 16 | I11: 92 | J11: 80 | K11: 1 | L11: 2.13
A12: 2026-01-02 | B12: (direct) / (none) | C12: Direct | D12: direct_none | E12: 44 | F12: 37 | G12: 20 | H12: 28 | I12: 95 | J12: 122 | K12: 0 | L12: 0
A13: 2026-01-02 | B13: partner_sites / referral | C13: Referral | D13: directory_referrals | E13: 24 | F13: 20 | G13: 14 | H13: 15 | I13: 109 | J13: 73 | K13: 0 | L13: 1.28
... A1087: 2026-06-30 | B1087: partner_sites / referral | C1087: Referral | D1087: agency_partner_backlinks | E1087: 37 | F1087: 28 | G1087: 20 | H1087: 23 | I1087: 113 | J1087: 126 | K1087: 1 | L1087: 1.77

Sheet Raw_GA4_Pages
A1: date | B1: landing_page | C1: page_title | D1: views | E1: users | F1: entrances | G1: engaged_sessions | H1: average_engagement_time_seconds | I1: form_submit_events | J1: phone_click_events | K1: whatsapp_click_events
A2: 2026-01-01 | B2: / | C2: Home | D2: 162 | E2: 91 | F2: 70 | G2: 41 | H2: 82 | I2: 0 | J2: 0 | K2: 1
A3: 2026-01-01 | B3: /services/business-website | C3: Business Website Development | D3: 123 | E3: 78 | F3: 36 | G3: 24 | H3: 115 | I3: 0 | J3: 0 | K3: 0
A4: 2026-01-01 | B4: /services/ecommerce-store | C4: Ecommerce Store Development | D4: 44 | E4: 31 | F4: 18 | G4: 12 | H4: 62 | I4: 0 | J4: 0 | K4: 0
A5: 2026-01-01 | B5: /services/seo-digital-marketing | C5: SEO & Digital Marketing | D5: 42 | E5: 29 | F5: 17 | G5: 10 | H5: 99 | I5: 0 | J5: 0 | K5: 0
A6: 2026-01-01 | B6: /services/school-management-system | C6: School Management System | D6: 35 | E6: 25 | F6: 16 | G6: 10 | H6: 88 | I6: 0 | J6: 0 | K6: 0
A7: 2026-01-01 | B7: /services/law-firm-management-system | C7: Law Firm Management System | D7: 22 | E7: 16 | F7: 8 | G7: 5 | H7: 109 | I7: 0 | J7: 0 | K7: 0
A8: 2026-01-01 | B8: /portfolio | C8: Portfolio | D8: 33 | E8: 20 | F8: 17 | G8: 12 | H8: 99 | I8: 0 | J8: 0 | K8: 0
A9: 2026-01-01 | B9: /blog/website-cost-nepal | C9: Website Cost in Nepal Guide | D9: 32 | E9: 24 | F9: 10 | G9: 7 | H9: 119 | I9: 0 | J9: 0 | K9: 0
A10: 2026-01-01 | B10: /contact | C10: Contact | D10: 22 | E10: 13 | F10: 10 | G10: 5 | H10: 75 | I10: 0 | J10: 0 | K10: 0
A11: 2026-01-01 | B11: /about | C11: About Digi Agent | D11: 6 | E11: 3 | F11: 2 | G11: 0 | H11: 81 | I11: 0 | J11: 0 | K11: 0
A12: 2026-01-02 | B12: / | C12: Home | D12: 146 | E12: 113 | F12: 59 | G12: 38 | H12: 90 | I12: 0 | J12: 0 | K12: 0
A13: 2026-01-02 | B13: /services/business-website | C13: Business Website Development | D13: 106 | E13: 65 | F13: 45 | G13: 28 | H13: 65 | I13: 0 | J13: 0 | K13: 0
... A1811: 2026-06-30 | B1811: /about | C1811: About Digi Agent | D1811: 12 | E1811: 7 | F1811: 6 | G1811: 2 | H1811: 68 | I1811: 0 | J1811: 0 | K1811: 0

Sheet Raw_GA4_Events
A1: date | B1: event_name | C1: page_path | D1: event_count | E1: users
A2: 2026-01-01 | B2: page_view | C2: / | D2: 162 | E2: 107
A3: 2026-01-01 | B3: scroll | C3: / | D3: 60 | E3: 49
A4: 2026-01-01 | B4: whatsapp_click | C4: / | D4: 1 | E4: 1
A5: 2026-01-01 | B5: page_view | C5: /services/business-website | D5: 123 | E5: 105
A6: 2026-01-01 | B6: scroll | C6: /services/business-website | D6: 58 | E6: 44
A7: 2026-01-01 | B7: page_view | C7: /services/ecommerce-store | D7: 44 | E7: 35
A8: 2026-01-01 | B8: scroll | C8: /services/ecommerce-store | D8: 21 | E8: 17
A9: 2026-01-01 | B9: page_view | C9: /services/seo-digital-marketing | D9: 42 | E9: 36
A10: 2026-01-01 | B10: scroll | C10: /services/seo-digital-marketing | D10: 19 | E10: 14
A11: 2026-01-01 | B11: page_view | C11: /services/school-management-system | D11: 35 | E11: 28
A12: 2026-01-01 | B12: scroll | C12: /services/school-management-system | D12: 21 | E12: 15
A13: 2026-01-01 | B13: page_view | C13: /services/law-firm-management-system | D13: 22 | E13: 19
... A4154: 2026-06-30 | B4154: scroll | C4154: /about | D4154: 4 | E4154: 2

Sheet Raw_GSC
A1: date | B1: query | C1: page | D1: country | E1: device | F1: clicks | G1: impressions | H1: ctr | I1: average_position
A2: 2026-01-01 | B2: website design company in nepal | C2: /services/business-website | D2: Nepal | E2: mobile | F2: 2 | G2: 177 | H2: 0.0113 | I2: 9.4
A3: 2026-01-01 | B3: ecommerce website development nepal | C3: /services/ecommerce-store | D3: Nepal | E3: desktop | F3: 3 | G3: 233 | H3: 0.0129 | I3: 9.2
A4: 2026-01-01 | B4: school management software nepal | C4: /services/school-management-system | D4: Nepal | E4: mobile | F4: 2 | G4: 125 | H4: 0.016 | I4: 11.8
A5: 2026-01-01 | B5: law firm management system nepal | C5: /services/law-firm-management-system | D5: Nepal | E5: mobile | F5: 1 | G5: 86 | H5: 0.0116 | I5: 11.2
A6: 2026-01-01 | B6: digital marketing company in nepal | C6: /services/seo-digital-marketing | D6: Nepal | E6: desktop | F6: 2 | G6: 173 | H6: 0.0116 | I6: 10.9
A7: 2026-01-01 | B7: business website package nepal | C7: /services/business-website | D7: Nepal | E7: mobile | F7: 2 | G7: 130 | H7: 0.0154 | I7: 8.2
A8: 2026-01-01 | B8: online store development nepal | C8: /services/ecommerce-store | D8: Nepal | E8: mobile | F8: 0 | G8: 71 | H8: 0 | I8: 9.8
A9: 2026-01-01 | B9: best IT company in kathmandu | C9: / | D9: Nepal | E9: desktop | F9: 0 | G9: 57 | H9: 0 | I9: 13.4
A10: 2026-01-01 | B10: portfolio website design nepal | C10: /portfolio | D10: Nepal | E10: mobile | F10: 0 | G10: 58 | H10: 0 | I10: 13.7
A11: 2026-01-01 | B11: crm software nepal | C11: /services/business-website | D11: Nepal | E11: desktop | F11: 0 | G11: 16 | H11: 0 | I11: 16.7
A12: 2026-01-01 | B12: wordpress website design nepal | C12: /services/business-website | D12: Nepal | E12: desktop | F12: 0 | G12: 9 | H12: 0 | I12: 17.8
A13: 2026-01-02 | B13: website design company in nepal | C13: /services/business-website | D13: Nepal | E13: mobile | F13: 2 | G13: 149 | H13: 0.0134 | I13: 10.1
... A2114: 2026-06-30 | B2114: wordpress website design nepal | C2114: /services/business-website | D2114: Nepal | E2114: desktop | F2114: 0 | G2114: 25 | H2114: 0 | I2114: 14.2

Sheet Raw_CRM_Leads
A1: lead_id | B1: lead_created_date | C1: source_medium | D1: default_channel_group | E1: campaign_name | F1: landing_page | G1: service_interest | H1: lead_status | I1: is_mql | J1: is_sql | K1: became_customer | L1: estimated_deal_value_usd | M1: city | N1: customer_type
A2: DG1001 | B2: 2026-01-01 | C2: google / organic | D2: Organic Search | E2: organic_non_brand | F2: / | G2: General Website Inquiry | H2: Working | I2: No | J2: No | K2: No | L2: 0 | M2: Biratnagar | N2: Professional Services
A3: DG1002 | B3: 2026-01-01 | C3: google / organic | D3: Organic Search | E3: organic_non_brand | F3: /blog/website-cost-nepal | G3: Business Website | H3: MQL | I3: Yes | J3: No | K3: No | L3: 0 | M3: Lalitpur | N3: Startup
A4: DG1003 | B4: 2026-01-01 | C4: google / organic | D4: Organic Search | E4: organic_non_brand | F4: /services/ecommerce-store | G4: Ecommerce Store | H4: MQL | I4: Yes | J4: No | K4: No | L4: 0 | M4: Pokhara | N4: SME
A5: DG1004 | B5: 2026-01-01 | C5: google / organic | D5: Organic Search | E5: organic_non_brand | F5: /services/business-website | G5: Business Website | H5: MQL | I5: Yes | J5: No | K5: No | L5: 0 | M5: Chitwan | N5: Professional Services
A6: DG1005 | B6: 2026-01-01 | C6: google / organic | D6: Organic Search | E6: organic_non_brand | F6: /services/business-website | G6: Business Website | H6: Working | I6: No | J6: No | K6: No | L6: 0 | M6: Hetauda | N6: Startup
A7: DG1006 | B7: 2026-01-01 | C7: google / cpc | D7: Paid Search | E7: google_ecommerce_leads | F7: /portfolio | G7: Portfolio Follow-up | H7: Working | I7: No | J7: No | K7: No | L7: 0 | M7: Pokhara | N7: SME
A8: DG1007 | B8: 2026-01-01 | C8: google / cpc | D8: Paid Search | E8: google_ecommerce_leads | F8: /services/ecommerce-store | G8: Ecommerce Store | H8: MQL | I8: Yes | J8: No | K8: No | L8: 0 | M8: Kathmandu | N8: SME
A9: DG1008 | B9: 2026-01-01 | C9: google / cpc | D9: Paid Search | E9: google_ecommerce_leads | F9: /services/ecommerce-store | G9: Ecommerce Store | H9: Working | I9: No | J9: No | K9: No | L9: 0 | M9: Dharan | N9: Educational Institution
A10: DG1009 | B10: 2026-01-01 | C10: facebook / paid_social | D10: Paid Social | E10: fb_business_website_awareness | F10: /about | G10: General Website Inquiry | H10: Working | I10: No | J10: No | K10: No | L10: 0 | M10: Bhaktapur | N10: SME
A11: DG1010 | B11: 2026-01-01 | C11: facebook / paid_social | D11: Paid Social | E11: fb_business_website_awareness | F11: /services/business-website | G11: Business Website | H11: Working | I11: No | J11: No | K11: No | L11: 0 | M11: Hetauda | N11: Startup
A12: DG1011 | B12: 2026-01-01 | C12: newsletter / email | D12: Email | E12: client_referral_nurture | F12: /services/seo-digital-marketing | G12: Digital Marketing | H12: MQL | I12: Yes | J12: No | K12: No | L12: 0 | M12: Bhaktapur | N12: Startup
A13: DG1012 | B13: 2026-01-01 | C13: newsletter / email | D13: Email | E13: client_referral_nurture | F13: /contact | G13: General Website Inquiry | H13: SQL | I13: Yes | J13: Yes | K13: No | L13: 0 | M13: Lalitpur | N13: Retail Business
... A2882: DG3881 | B2882: 2026-06-30 | C2882: partner_sites / referral | D2882: Referral | E2882: agency_partner_backlinks | F2882: / | G2882: General Website Inquiry | H2882: Working | I2882: No | J2882: No | K2882: No | L2882: 0 | M2882: Dharan | N2882: Retail Business

Sheet Clean_Daily_Performance
A1: Date | B1: Month | C1: Channel | D1: Sessions | E1: Users | F1: Engaged Sessions | G1: Engagement Rate | H1: Key Events | I1: Website Key Event CVR | J1: CRM Leads | K1: Lead Rate | L1: MQLs | M1: MQL Rate | N1: SQLs | O1: Customers | P1: Lead-to-Customer Rate | Q1: Estimated Revenue | R1: Cost | S1: CPA | T1: Revenue per Session | U1: ROAS | V1: Insight Tag
A2: 2026-01-01 | B2: 2026-01 | C2: Direct | D2: 41 | E2: 31 | F2: 24 | G2: =IFERROR(F2/D2,0) -> 0.58536585 | H2: 2 | I2: =IFERROR(H2/D2,0) -> 0.048780488 | J2: 1 | K2: =IFERROR(J2/D2,0) -> 0.024390244 | L2: 1 | M2: =IFERROR(L2/J2,0) -> 1 | N2: 0 | O2: 0 | P2: =IFERROR(O2/J2,0) -> 0 | Q2: 0 | R2: 0 | S2: =IF(J2=0,"",R2/J2) -> 0 | T2: =IFERROR(Q2/D2,0) -> 0 | U2: =IF(R2=0,"",Q2/R2) | V2: Baseline
A3: 2026-01-01 | B3: 2026-01 | C3: Email | D3: 18 | E3: 13 | F3: 15 | G3: =IFERROR(F3/D3,0) -> 0.83333333 | H3: 1 | I3: =IFERROR(H3/D3,0) -> 0.055555556 | J3: 2 | K3: =IFERROR(J3/D3,0) -> 0.11111111 | L3: 2 | M3: =IFERROR(L3/J3,0) -> 1 | N3: 1 | O3: 0 | P3: =IFERROR(O3/J3,0) -> 0 | Q3: 0 | R3: 1.5 | S3: =IF(J3=0,"",R3/J3) -> 0.75 | T3: =IFERROR(Q3/D3,0) -> 0 | U3: =IF(R3=0,"",Q3/R3) -> 0 | V3: Small volume, high intent
A4: 2026-01-01 | B4: 2026-01 | C4: Organic Search | D4: 131 | E4: 94 | F4: 90 | G4: =IFERROR(F4/D4,0) -> 0.6870229 | H4: 6 | I4: =IFERROR(H4/D4,0) -> 0.045801527 | J4: 5 | K4: =IFERROR(J4/D4,0) -> 0.038167939 | L4: 3 | M4: =IFERROR(L4/J4,0) -> 0.6 | N4: 0 | O4: 0 | P4: =IFERROR(O4/J4,0) -> 0 | Q4: 0 | R4: 23.41 | S4: =IF(J4=0,"",R4/J4) -> 4.682 | T4: =IFERROR(Q4/D4,0) -> 0 | U4: =IF(R4=0,"",Q4/R4) -> 0 | V4: SEO engagement strength
A5: 2026-01-01 | B5: 2026-01 | C5: Paid Search | D5: 52 | E5: 39 | F5: 31 | G5: =IFERROR(F5/D5,0) -> 0.59615385 | H5: 2 | I5: =IFERROR(H5/D5,0) -> 0.038461538 | J5: 3 | K5: =IFERROR(J5/D5,0) -> 0.057692308 | L5: 1 | M5: =IFERROR(L5/J5,0) -> 0.33333333 | N5: 0 | O5: 0 | P5: =IFERROR(O5/J5,0) -> 0 | Q5: 0 | R5: 59.34 | S5: =IF(J5=0,"",R5/J5) -> 19.78 | T5: =IFERROR(Q5/D5,0) -> 0 | U5: =IF(R5=0,"",Q5/R5) -> 0 | V5: Baseline
A6: 2026-01-01 | B6: 2026-01 | C6: Paid Social | D6: 87 | E6: 73 | F6: 43 | G6: =IFERROR(F6/D6,0) -> 0.49425287 | H6: 4 | I6: =IFERROR(H6/D6,0) -> 0.045977011 | J6: 2 | K6: =IFERROR(J6/D6,0) -> 0.022988506 | L6: 0 | M6: =IFERROR(L6/J6,0) -> 0 | N6: 0 | O6: 0 | P6: =IFERROR(O6/J6,0) -> 0 | Q6: 0 | R6: 35.59 | S6: =IF(J6=0,"",R6/J6) -> 17.795 | T6: =IFERROR(Q6/D6,0) -> 0 | U6: =IF(R6=0,"",Q6/R6) -> 0 | V6: High traffic, low lead efficiency
A7: 2026-01-01 | B7: 2026-01 | C7: Referral | D7: 29 | E7: 24 | F7: 19 | G7: =IFERROR(F7/D7,0) -> 0.65517241 | H7: 1 | I7: =IFERROR(H7/D7,0) -> 0.034482759 | J7: 1 | K7: =IFERROR(J7/D7,0) -> 0.034482759 | L7: 1 | M7: =IFERROR(L7/J7,0) -> 1 | N7: 0 | O7: 0 | P7: =IFERROR(O7/J7,0) -> 0 | Q7: 0 | R7: 1.42 | S7: =IF(J7=0,"",R7/J7) -> 1.42 | T7: =IFERROR(Q7/D7,0) -> 0 | U7: =IF(R7=0,"",Q7/R7) -> 0 | V7: Baseline
A8: 2026-01-02 | B8: 2026-01 | C8: Direct | D8: 44 | E8: 37 | F8: 28 | G8: =IFERROR(F8/D8,0) -> 0.63636364 | H8: 0 | I8: =IFERROR(H8/D8,0) -> 0 | J8: 3 | K8: =IFERROR(J8/D8,0) -> 0.068181818 | L8: 0 | M8: =IFERROR(L8/J8,0) -> 0 | N8: 0 | O8: 0 | P8: =IFERROR(O8/J8,0) -> 0 | Q8: 0 | R8: 0 | S8: =IF(J8=0,"",R8/J8) -> 0 | T8: =IFERROR(Q8/D8,0) -> 0 | U8: =IF(R8=0,"",Q8/R8) | V8: Baseline
A9: 2026-01-02 | B9: 2026-01 | C9: Email | D9: 22 | E9: 19 | F9: 16 | G9: =IFERROR(F9/D9,0) -> 0.72727273 | H9: 1 | I9: =IFERROR(H9/D9,0) -> 0.045454545 | J9: 2 | K9: =IFERROR(J9/D9,0) -> 0.090909091 | L9: 1 | M9: =IFERROR(L9/J9,0) -> 0.5 | N9: 1 | O9: 0 | P9: =IFERROR(O9/J9,0) -> 0 | Q9: 0 | R9: 2.13 | S9: =IF(J9=0,"",R9/J9) -> 1.065 | T9: =IFERROR(Q9/D9,0) -> 0 | U9: =IF(R9=0,"",Q9/R9) -> 0 | V9: Small volume, high intent
A10: 2026-01-02 | B10: 2026-01 | C10: Organic Search | D10: 137 | E10: 110 | F10: 89 | G10: =IFERROR(F10/D10,0) -> 0.64963504 | H10: 6 | I10: =IFERROR(H10/D10,0) -> 0.04379562 | J10: 5 | K10: =IFERROR(J10/D10,0) -> 0.03649635 | L10: 3 | M10: =IFERROR(L10/J10,0) -> 0.6 | N10: 2 | O10: 0 | P10: =IFERROR(O10/J10,0) -> 0 | Q10: 0 | R10: 27.1 | S10: =IF(J10=0,"",R10/J10) -> 5.42 | T10: =IFERROR(Q10/D10,0) -> 0 | U10: =IF(R10=0,"",Q10/R10) -> 0 | V10: SEO engagement strength
A11: 2026-01-02 | B11: 2026-01 | C11: Paid Search | D11: 71 | E11: 57 | F11: 45 | G11: =IFERROR(F11/D11,0) -> 0.63380282 | H11: 4 | I11: =IFERROR(H11/D11,0) -> 0.056338028 | J11: 3 | K11: =IFERROR(J11/D11,0) -> 0.042253521 | L11: 2 | M11: =IFERROR(L11/J11,0) -> 0.66666667 | N11: 1 | O11: 0 | P11: =IFERROR(O11/J11,0) -> 0 | Q11: 0 | R11: 89.63 | S11: =IF(J11=0,"",R11/J11) -> 29.876667 | T11: =IFERROR(Q11/D11,0) -> 0 | U11: =IF(R11=0,"",Q11/R11) -> 0 | V11: Baseline
A12: 2026-01-02 | B12: 2026-01 | C12: Paid Social | D12: 90 | E12: 74 | F12: 35 | G12: =IFERROR(F12/D12,0) -> 0.38888889 | H12: 1 | I12: =IFERROR(H12/D12,0) -> 0.011111111 | J12: 2 | K12: =IFERROR(J12/D12,0) -> 0.022222222 | L12: 1 | M12: =IFERROR(L12/J12,0) -> 0.5 | N12: 1 | O12: 0 | P12: =IFERROR(O12/J12,0) -> 0 | Q12: 0 | R12: 40.25 | S12: =IF(J12=0,"",R12/J12) -> 20.125 | T12: =IFERROR(Q12/D12,0) -> 0 | U12: =IF(R12=0,"",Q12/R12) -> 0 | V12: High traffic, low lead efficiency
A13: 2026-01-02 | B13: 2026-01 | C13: Referral | D13: 24 | E13: 20 | F13: 15 | G13: =IFERROR(F13/D13,0) -> 0.625 | H13: 0 | I13: =IFERROR(H13/D13,0) -> 0 | J13: 1 | K13: =IFERROR(J13/D13,0) -> 0.041666667 | L13: 0 | M13: =IFERROR(L13/J13,0) -> 0 | N13: 0 | O13: 0 | P13: =IFERROR(O13/J13,0) -> 0 | Q13: 0 | R13: 1.28 | S13: =IF(J13=0,"",R13/J13) -> 1.28 | T13: =IFERROR(Q13/D13,0) -> 0 | U13: =IF(R13=0,"",Q13/R13) -> 0 | V13: Baseline
... A1087: 2026-06-30 | B1087: 2026-06 | C1087: Referral | D1087: 37 | E1087: 28 | F1087: 23 | G1087: =IFERROR(F1087/D1087,0) -> 0.62162162 | H1087: 1 | I1087: =IFERROR(H1087/D1087,0) -> 0.027027027 | J1087: 2 | K1087: =IFERROR(J1087/D1087,0) -> 0.054054054 | L1087: 1 | M1087: =IFERROR(L1087/J1087,0) -> 0.5 | N1087: 1 | O1087: 0 | P1087: =IFERROR(O1087/J1087,0) -> 0 | Q1087: 0 | R1087: 1.77 | S1087: =IF(J1087=0,"",R1087/J1087) -> 0.885 | T1087: =IFERROR(Q1087/D1087,0) -> 0 | U1087: =IF(R1087=0,"",Q1087/R1087) -> 0 | V1087: Baseline

Sheet Landing_Page_Funnel
A1: Landing Page | B1: Page Title | C1: Views | D1: Users | E1: Entrances | F1: Engaged Sessions | G1: Avg Engagement Time Sec | H1: Form Submits | I1: Phone Clicks | J1: WhatsApp Clicks | K1: CRM Leads | L1: Landing Lead Rate | M1: MQLs | N1: SQLs | O1: Customers | P1: Estimated Revenue | Q1: Recommendation
A2: /services/business-website | B2: Business Website Development | C2: 19162 | D2: 12644 | E2: 7571 | F2: 4683 | G2: 90.5 | H2: 72 | I2: 17 | J2: 89 | K2: 556 | L2: =IFERROR(K2/E2,0) -> 0.073438119 | M2: 248 | N2: 81 | O2: 8 | P2: 4660.31 | Q2: Improve service copy, FAQs, and CTA placement.
A3: /services/ecommerce-store | B3: Ecommerce Store Development | C3: 15726 | D3: 10339 | E3: 6321 | F3: 4076 | G3: 90.9 | H3: 71 | I3: 29 | J3: 105 | K3: 521 | L3: =IFERROR(K3/E3,0) -> 0.082423667 | M3: 261 | N3: 78 | O3: 10 | P3: 7416.08 | Q3: Scale high-intent paid search and add clearer package/pricing CTA.
A4: / | B4: Home | C4: 28967 | D4: 19108 | E4: 11389 | F4: 6544 | G4: 78.4 | H4: 48 | I4: 8 | J4: 75 | K4: 459 | L4: =IFERROR(K4/E4,0) -> 0.040302046 | M4: 216 | N4: 66 | O4: 11 | P4: 7743.83 | Q4: Move users from homepage into service-specific landing pages faster.
A5: /services/seo-digital-marketing | B5: SEO & Digital Marketing | C5: 13736 | D5: 9087 | E5: 5430 | F5: 3234 | G5: 84.9 | H5: 20 | I5: 1 | J5: 30 | K5: 347 | L5: =IFERROR(K5/E5,0) -> 0.063904236 | M5: 167 | N5: 43 | O5: 7 | P5: 4838.39 | Q5: Improve service copy, FAQs, and CTA placement.
A6: /services/school-management-system | B6: School Management System | C6: 7812 | D6: 5105 | E6: 3043 | F6: 1917 | G6: 91.1 | H6: 1 | I6: 0 | J6: 2 | K6: 252 | L6: =IFERROR(K6/E6,0) -> 0.082813013 | M6: 122 | N6: 44 | O6: 6 | P6: 5095.48 | Q6: Improve service copy, FAQs, and CTA placement.
A7: /contact | B7: Contact | C7: 4421 | D7: 2859 | E7: 1637 | F7: 787 | G7: 74.8 | H7: 0 | I7: 0 | J7: 0 | K7: 246 | L7: =IFERROR(K7/E7,0) -> 0.15027489 | M7: 109 | N7: 37 | O7: 6 | P7: 4012.91 | Q7: Reduce form friction and keep WhatsApp/phone CTA visible above fold.
A8: /portfolio | B8: Portfolio | C8: 9086 | D8: 5928 | E8: 3602 | F8: 2430 | G8: 101.9 | H8: 1 | I8: 0 | J8: 0 | K8: 209 | L8: =IFERROR(K8/E8,0) -> 0.05802332 | M8: 101 | N8: 25 | O8: 4 | P8: 2890.22 | Q8: Add proof-based CTA under each case study to capture high-intent visitors.
A9: /blog/website-cost-nepal | B9: Website Cost in Nepal Guide | C9: 10197 | D9: 6527 | E9: 3956 | F9: 2725 | G9: 97.3 | H9: 0 | I9: 0 | J9: 4 | K9: 137 | L9: =IFERROR(K9/E9,0) -> 0.03463094 | M9: 60 | N9: 15 | O9: 3 | P9: 2096.18 | Q9: Add stronger internal links to service pages and downloadable lead magnet.
A10: /services/law-firm-management-system | B10: Law Firm Management System | C10: 5572 | D10: 3631 | E10: 2124 | F10: 1348 | G10: 99.4 | H10: 0 | I10: 0 | J10: 0 | K10: 128 | L10: =IFERROR(K10/E10,0) -> 0.060263653 | M10: 59 | N10: 23 | O10: 4 | P10: 2589.45 | Q10: Improve service copy, FAQs, and CTA placement.
A11: /about | B11: About Digi Agent | C11: 2187 | D11: 1336 | E11: 795 | F11: 326 | G11: 73.9 | H11: 0 | I11: 0 | J11: 0 | K11: 26 | L11: =IFERROR(K11/E11,0) -> 0.032704403 | M11: 13 | N11: 5 | O11: 0 | P11: 0 | Q11: Improve service copy, FAQs, and CTA placement.

Sheet SEO_Query_Analysis
A1: Query | B1: Page | C1: Clicks | D1: Impressions | E1: CTR | F1: Avg Position | G1: Opportunity
A2: website cost in nepal | B2: /blog/website-cost-nepal | C2: 2008 | D2: 58486 | E2: =IFERROR(C2/D2,0) -> 0.034333003 | F2: 4.9 | G2: Monitor performance and test content updates.
A3: ecommerce website development nepal | B3: /services/ecommerce-store | C3: 1071 | D3: 39977 | E3: =IFERROR(C3/D3,0) -> 0.026790404 | F3: 6.3 | G3: Monitor performance and test content updates.
A4: website design company in nepal | B4: /services/business-website | C4: 874 | D4: 45262 | E4: =IFERROR(C4/D4,0) -> 0.019309796 | F4: 7.4 | G4: Ranking is visible but CTR is low. Improve title tag and meta description.
A5: digital marketing company in nepal | B5: /services/seo-digital-marketing | C5: 652 | D5: 37990 | E5: =IFERROR(C5/D5,0) -> 0.017162411 | F5: 8.2 | G5: Ranking is visible but CTR is low. Improve title tag and meta description.
A6: school management software nepal | B6: /services/school-management-system | C6: 525 | D6: 35118 | E6: =IFERROR(C6/D6,0) -> 0.014949598 | F6: 9.2 | G6: Ranking is visible but CTR is low. Improve title tag and meta description.
A7: business website package nepal | B7: /services/business-website | C7: 385 | D7: 24604 | E7: =IFERROR(C7/D7,0) -> 0.015647862 | F7: 8 | G7: Ranking is visible but CTR is low. Improve title tag and meta description.
A8: online store development nepal | B8: /services/ecommerce-store | C8: 262 | D8: 21567 | E8: =IFERROR(C8/D8,0) -> 0.012148189 | F8: 10.3 | G8: High impression query outside top 10. Strengthen content depth, internal links, and FAQ section.
A9: law firm management system nepal | B9: /services/law-firm-management-system | C9: 221 | D9: 21314 | E9: =IFERROR(C9/D9,0) -> 0.010368772 | F9: 11.3 | G9: High impression query outside top 10. Strengthen content depth, internal links, and FAQ section.
A10: best IT company in kathmandu | B10: / | C10: 128 | D10: 15405 | E10: =IFERROR(C10/D10,0) -> 0.0083089906 | F10: 12 | G10: High impression query outside top 10. Strengthen content depth, internal links, and FAQ section.
A11: portfolio website design nepal | B11: /portfolio | C11: 41 | D11: 12215 | E11: =IFERROR(C11/D11,0) -> 0.0033565289 | F11: 13.5 | G11: Monitor performance and test content updates.
A12: crm software nepal | B12: /services/business-website | C12: 0 | D12: 3047 | E12: =IFERROR(C12/D12,0) -> 0 | F12: 17.3 | G12: Monitor performance and test content updates.
A13: wordpress website design nepal | B13: /services/business-website | C13: 0 | D13: 3005 | E13: =IFERROR(C13/D13,0) -> 0 | F13: 15.9 | G13: Monitor performance and test content updates.

Sheet Monthly_Summary
A1: Month | B1: Channel | C1: Sessions | D1: Leads | E1: Customers | F1: Estimated Revenue | G1: Cost
A2: 2026-01 | B2: Direct | C2: 1485 | D2: 54 | E2: 2 | F2: 927.69 | G2: 0
A3: 2026-01 | B3: Email | C3: 603 | D3: 44 | E3: 2 | F3: 1738.63 | G3: 55.8
A4: 2026-01 | B4: Organic Search | C4: 3715 | D4: 135 | E4: 0 | F4: 0 | G4: 681.87
A5: 2026-01 | B5: Paid Search | C5: 1826 | D5: 89 | E5: 2 | F5: 1181.35 | G5: 2090.72
A6: 2026-01 | B6: Paid Social | C6: 2408 | D6: 64 | E6: 0 | F6: 0 | G6: 1011.82
A7: 2026-01 | B7: Referral | C7: 758 | D7: 29 | E7: 0 | F7: 0 | G7: 38.35
A8: 2026-02 | B8: Direct | C8: 1391 | D8: 41 | E8: 0 | F8: 0 | G8: 0
A9: 2026-02 | B9: Email | C9: 569 | D9: 41 | E9: 2 | F9: 1152.11 | G9: 51.14
A10: 2026-02 | B10: Organic Search | C10: 3595 | D10: 125 | E10: 5 | F10: 3376.66 | G10: 655.82
A11: 2026-02 | B11: Paid Search | C11: 1782 | D11: 88 | E11: 2 | F11: 1480.01 | G11: 2054.86
A12: 2026-02 | B12: Paid Social | C12: 2701 | D12: 72 | E12: 0 | F12: 0 | G12: 1154.49
A13: 2026-02 | B13: Referral | C13: 702 | D13: 27 | E13: 2 | F13: 1486.54 | G13: 35.39
... A37: 2026-06 | B37: Referral | C37: 947 | D37: 34 | E37: 1 | F37: 635.25 | G37: 48.27

Sheet Dashboard
A1: Digi Agent Website & GA4 Funnel Analytics Dashboard | O1: Channel | P1: Sessions | Q1: Leads | R1: Customers | S1: Revenue | T1: Cost
A2: Period: 2026-01-01 to 2026-06-30 | Synthetic portfolio data | Objective: find quality lead drivers | O2: Organic Search | P2: 30251 | Q2: 1079 | R2: 15 | S2: 9934.51 | T2: 5552.43
O3: Paid Social | P3: 15096 | Q3: 391 | R3: 3 | S3: 2047.57 | T3: 6454.89
A4: Sessions | B4: Engagement Rate | C4: Key Event CVR | D4: CRM Leads | E4: Customers | F4: Revenue | G4: Cost | H4: ROAS | O4: Paid Search | P4: 12887 | Q4: 643 | R4: 20 | S4: 15485.33 | T4: 14973.48
A5: =SUM(Clean_Daily_Performance!D:D) -> 76906 | B5: =SUM(Clean_Daily_Performance!F:F)/SUM(Clean_Daily_Performance!D:D) -> 0.60419213 | C5: =SUM(Clean_Daily_Performance!H:H)/SUM(Clean_Daily_Performance!D:D) -> 0.039606793 | D5: =SUM(Clean_Daily_Performance!J:J) -> 2881 | E5: =SUM(Clean_Daily_Performance!O:O) -> 59 | F5: =SUM(Clean_Daily_Performance!Q:Q) -> 41342.85 | G5: =SUM(Clean_Daily_Performance!R:R) -> 27613.9 | H5: =SUM(Clean_Daily_Performance!Q:Q)/SUM(Clean_Daily_Performance!R:R) -> 1.4971753 | O5: Direct | P5: 9416 | Q5: 290 | R5: 2 | S5: 927.69 | T5: 0
O6: Referral | P6: 5178 | Q6: 194 | R6: 6 | S6: 3888.41 | T6: 261.83
O7: Email | P7: 4078 | Q7: 284 | R7: 13 | S7: 9059.34 | T7: 371.27
A8: Channel Performance Summary
A9: Channel | B9: Sessions | C9: Users | D9: Engagement Rate | E9: Key Event CVR | F9: Leads | G9: MQLs | H9: Customers | I9: Revenue | J9: Cost | K9: CPA | L9: ROAS | M9: Main Recommendation
A10: Organic Search | B10: 30251 | C10: 24156 | D10: =IFERROR(SUMIFS(Clean_Daily_Performance!F:F,Clean_Daily_Performance!C:C,A10)/SUMIFS(Clean_Daily_Performance!D:D,Clean_Daily_Performance!C:C,A10),0) -> 0.66768041 | E10: =IFERROR(SUMIFS(Clean_Daily_Performance!H:H,Clean_Daily_Performance!C:C,A10)/SUMIFS(Clean_Daily_Performance!D:D,Clean_Daily_Performance!C:C,A10),0) -> 0.043568808 | F10: 1079 | G10: 484 | H10: 15 | I10: 9934.51 | J10: 5552.43 | K10: =IF(F10=0,"",J10/F10) -> 5.1459036 | L10: =IF(J10=0,"",I10/J10) -> 1.7892184 | M10: Protect SEO growth; improve service-page CTAs to convert more organic visitors.
A11: Paid Search | B11: 12887 | C11: 10190 | D11: =IFERROR(SUMIFS(Clean_Daily_Performance!F:F,Clean_Daily_Performance!C:C,A11)/SUMIFS(Clean_Daily_Performance!D:D,Clean_Daily_Performance!C:C,A11),0) -> 0.6027004 | E11: =IFERROR(SUMIFS(Clean_Daily_Performance!H:H,Clean_Daily_Performance!C:C,A11)/SUMIFS(Clean_Daily_Performance!D:D,Clean_Daily_Performance!C:C,A11),0) -> 0.053930317 | F11: 643 | G11: 370 | H11: 20 | I11: 15485.33 | J11: 14973.48 | K11: =IF(F11=0,"",J11/F11) -> 23.286905 | L11: =IF(J11=0,"",I11/J11) -> 1.0341838 | M11: Keep budget on high-intent service keywords; monitor CPA by service page.
A12: Paid Social | B12: 15096 | C12: 12006 | D12: =IFERROR(SUMIFS(Clean_Daily_Performance!F:F,Clean_Daily_Performance!C:C,A12)/SUMIFS(Clean_Daily_Performance!D:D,Clean_Daily_Performance!C:C,A12),0) -> 0.47383413 | E12: =IFERROR(SUMIFS(Clean_Daily_Performance!H:H,Clean_Daily_Performance!C:C,A12)/SUMIFS(Clean_Daily_Performance!D:D,Clean_Daily_Performance!C:C,A12),0) -> 0.025238474 | F12: 391 | G12: 110 | H12: 3 | I12: 2047.57 | J12: 6454.89 | K12: =IF(F12=0,"",J12/F12) -> 16.50867 | L12: =IF(J12=0,"",I12/J12) -> 0.31721222 | M12: Use for retargeting and proof-based creatives, not broad traffic alone.
A13: Direct | B13: 9416 | C13: 7456 | D13: =IFERROR(SUMIFS(Clean_Daily_Performance!F:F,Clean_Daily_Performance!C:C,A13)/SUMIFS(Clean_Daily_Performance!D:D,Clean_Daily_Performance!C:C,A13),0) -> 0.5574554 | E13: =IFERROR(SUMIFS(Clean_Daily_Performance!H:H,Clean_Daily_Performance!C:C,A13)/SUMIFS(Clean_Daily_Performance!D:D,Clean_Daily_Performance!C:C,A13),0) -> 0.028887001 | F13: 290 | G13: 126 | H13: 2 | I13: 927.69 | J13: 0 | K13: =IF(F13=0,"",J13/F13) -> 0 | L13: =IF(J13=0,"",I13/J13) | M13: Improve brand recall measurement and ask leads how they heard about Digi Agent.
A14: Email | B14: 4078 | C14: 3188 | D14: =IFERROR(SUMIFS(Clean_Daily_Performance!F:F,Clean_Daily_Performance!C:C,A14)/SUMIFS(Clean_Daily_Performance!D:D,Clean_Daily_Performance!C:C,A14),0) -> 0.71971555 | E14: =IFERROR(SUMIFS(Clean_Daily_Performance!H:H,Clean_Daily_Performance!C:C,A14)/SUMIFS(Clean_Daily_Performance!D:D,Clean_Daily_Performance!C:C,A14),0) -> 0.061794998 | F14: 284 | G14: 177 | H14: 13 | I14: 9059.34 | J14: 371.27 | K14: =IF(F14=0,"",J14/F14) -> 1.3072887 | L14: =IF(J14=0,"",I14/J14) -> 24.400948 | M14: Use as nurture channel for warm prospects; volume is small but lead quality is strong.
A15: Referral | B15: 5178 | C15: 4054 | D15: =IFERROR(SUMIFS(Clean_Daily_Performance!F:F,Clean_Daily_Performance!C:C,A15)/SUMIFS(Clean_Daily_Performance!D:D,Clean_Daily_Performance!C:C,A15),0) -> 0.61104674 | E15: =IFERROR(SUMIFS(Clean_Daily_Performance!H:H,Clean_Daily_Performance!C:C,A15)/SUMIFS(Clean_Daily_Performance!D:D,Clean_Daily_Performance!C:C,A15),0) -> 0.024719969 | F15: 194 | G15: 89 | H15: 6 | I15: 3888.41 | J15: 261.83 | K15: =IF(F15=0,"",J15/F15) -> 1.3496392 | L15: =IF(J15=0,"",I15/J15) -> 14.850896 | M15: Strengthen partner backlinks and directory listings that send qualified visitors.
A18: Executive Insights
A19: 1 | B19: Organic Search produced the largest demand pool and should be protected with service-page SEO and content updates.
A20: 2 | B20: Paid Search generated stronger intent and should be optimized around ecommerce and business website keywords.
A21: 3 | B21: Paid Social created traffic efficiently but lower lead quality; use it mainly for retargeting and proof-based creatives.
A22: 4 | B22: The ecommerce and business website pages are the strongest service pages for lead generation.
A23: 5 | B23: Search queries with high impressions but average positions outside the top 10 are the clearest SEO growth opportunities.
